PythonKuaisuJiaocheng/README.md
PythonKuaisuJiaocheng/__init__.py
PythonKuaisuJiaocheng/__main__.py
PythonKuaisuJiaocheng/file.epub
PythonKuaisuJiaocheng/index.html
PythonKuaisuJiaocheng/css/__init__.py
PythonKuaisuJiaocheng/css/annotations.css
PythonKuaisuJiaocheng/css/main.css
PythonKuaisuJiaocheng/css/normalize.css
PythonKuaisuJiaocheng/css/popup.css
PythonKuaisuJiaocheng/font/__init__.py
PythonKuaisuJiaocheng/font/fontello.eot
PythonKuaisuJiaocheng/font/fontello.svg
PythonKuaisuJiaocheng/font/fontello.ttf
PythonKuaisuJiaocheng/font/fontello.woff
PythonKuaisuJiaocheng/img/__init__.py
PythonKuaisuJiaocheng/img/annotator-glyph-sprite.png
PythonKuaisuJiaocheng/img/annotator-icon-sprite.png
PythonKuaisuJiaocheng/img/apple-touch-icon.png
PythonKuaisuJiaocheng/img/cancelfullscreen.png
PythonKuaisuJiaocheng/img/close.png
PythonKuaisuJiaocheng/img/fullscreen.png
PythonKuaisuJiaocheng/img/loader.gif
PythonKuaisuJiaocheng/img/menu-icon.png
PythonKuaisuJiaocheng/img/save.png
PythonKuaisuJiaocheng/img/saved.png
PythonKuaisuJiaocheng/img/settings-s.png
PythonKuaisuJiaocheng/img/settings.png
PythonKuaisuJiaocheng/img/star.png
PythonKuaisuJiaocheng/js/__init__.py
PythonKuaisuJiaocheng/js/epub.js
PythonKuaisuJiaocheng/js/epub.min.js
PythonKuaisuJiaocheng/js/epub.min.map
PythonKuaisuJiaocheng/js/hooks.min.js
PythonKuaisuJiaocheng/js/hooks.min.map
PythonKuaisuJiaocheng/js/reader.js
PythonKuaisuJiaocheng/js/reader.js.map
PythonKuaisuJiaocheng/js/reader.min.js
PythonKuaisuJiaocheng/js/reader.min.map
PythonKuaisuJiaocheng/js/hooks/__init__.py
PythonKuaisuJiaocheng/js/hooks/extensions/__init__.py
PythonKuaisuJiaocheng/js/hooks/extensions/highlight.js
PythonKuaisuJiaocheng/js/libs/__init__.py
PythonKuaisuJiaocheng/js/libs/jquery.min.js
PythonKuaisuJiaocheng/js/libs/localforage.min.js
PythonKuaisuJiaocheng/js/libs/screenfull.js
PythonKuaisuJiaocheng/js/libs/screenfull.min.js
PythonKuaisuJiaocheng/js/libs/zip.min.js
PythonKuaisuJiaocheng/js/plugins/__init__.py
python_kuaisu_jiaocheng-2024.3.1.0.dist-info/METADATA
python_kuaisu_jiaocheng-2024.3.1.0.dist-info/WHEEL
python_kuaisu_jiaocheng-2024.3.1.0.dist-info/entry_points.txt
python_kuaisu_jiaocheng-2024.3.1.0.dist-info/top_level.txt
python_kuaisu_jiaocheng-2024.3.1.0.dist-info/RECORD
